rest_db_client/__init__.py
rest_db_client/core.py
rest_db_client/utils.py
rest_db_client-2.2.0.dist-info/LICENSE.txt
rest_db_client-2.2.0.dist-info/METADATA
rest_db_client-2.2.0.dist-info/WHEEL
rest_db_client-2.2.0.dist-info/top_level.txt
rest_db_client-2.2.0.dist-info/RECORD
