Metadata-Version: 2.1
Name: rest-db-client
Version: 2.2.0
Summary: Client for RESTful databases
Home-page: https://gitlab.com/librecube/lib/python-rest-db-client
Author-email: info@librecube.org
License: MIT
Platform: UNKNOWN
Requires-Python: >=3
License-File: LICENSE.txt
Requires-Dist: requests
